Workbook

Sheet Master Deadlines
A1: First Mile — Master Deadline Reference
A2: This sheet is the source of truth. Add or edit deadlines here. Monthly tabs reference this data.
A4: # | B4: Day of Month | C4: Cadence | D4: Property / Fund | E4: Payment Type | F4: Task Description | G4: Task Owner | H4: Notes
A5: 1 | B5: 8th | C5: Monthly | D5: 41 Flatbush Ave | E5: AM Fee | F5: Receive JLL Financial Package from JLL. Invoice them for AM Fee - 2.5% | G5: Anthony
A6: 2 | B6: 8th | C6: Monthly | D6: Pref Fund I - Solow | E6: AM Fee | F6: Transfer Solow AM fees to FMC - $5,208 (BofA scheduled) | G6: BofA - automatic
A7: 3 | B7: 10th | C7: Monthly | D7: Paramus Plaza | E7: Reporting | F7: Upload Monthly Management Reports to DRA | G7: Anthony
A8: 4 | B8: 20th | C8: Monthly | D8: 61 S Paramus | E8: AM Fee | F8: Transfer distros from property to FM Paramus Member (BofA scheduled) | G8: BofA - automatic
A9: 5 | B9: 20th | C9: Quarterly | D9: Pref Fund II - JPY | E9: Investor Payment | F9: Purchase JPY to Goldman Sachs. Loan from FMC if cash shortfall. | G9: Anthony
A10: 6 | B10: 20th | C10: Quarterly | D10: Pref Fund II - JPY | E10: Investor Payment | F10: Send JPY to investors via Goldman Sachs | G10: Anthony
A11: 7 | B11: 21st | C11: Monthly | D11: 61 S Paramus | E11: AM Fee | F11: Transfer AM fee split 48k to FM and 4k to Ring (BofA scheduled) | G11: BofA - automatic
A12: 8 | B12: 23rd | C12: Monthly | D12: 1700 East Putnam | E12: Investor Payment | F12: Send Distros via Appfolio (*Currently Suspended) | G12: Xuan
A13: 9 | B13: 23rd | C13: Monthly | D13: 61 S Paramus | E13: Investor Payment | F13: Send Distros via Appfolio | G13: Anthony
A14: 10 | B14: 23rd | C14: Monthly | D14: One River Centre | E14: Investor Payment | F14: Send Distros via Appfolio (*Xuan sends for now, will be transferred soon to Anthony) | G14: Xuan
A15: 11 | B15: 23rd | C15: Monthly | D15: Paramus Plaza | E15: Investor Payment | F15: Send Distros via Appfolio | G15: Anthony
A16: 12 | B16: 23rd | C16: Monthly | D16: Pref Fund I - Solow | E16: Investor Payment | F16: Send Distros via Appfolio | G16: Anthony
... A18: 14 | B18: 25th | C18: Monthly | D18: Paramus Plaza | E18: AM Fee | F18: Pay Paramus Plaza AM Fee, if cash distro received by DRA | G18: Anthony

Sheet Summary
A1: First Mile — 2026 Completion Dashboard
A3: Month | B3: Total Tasks | C3: Completed | D3: Remaining | E3: % Done
A4: January | B4: 14 | C4: =COUNTIF(Jan!A5:A18,"Done") -> 0 | D4: =B4-C4 -> 14 | E4: =IF(B4>0,C4/B4,0) -> 0
A5: February | B5: 11 | C5: =COUNTIF(Feb!A5:A15,"Done") -> 0 | D5: =B5-C5 -> 11 | E5: =IF(B5>0,C5/B5,0) -> 0
A6: March | B6: 11 | C6: =COUNTIF(Mar!A5:A15,"Done") -> 0 | D6: =B6-C6 -> 11 | E6: =IF(B6>0,C6/B6,0) -> 0
A7: April | B7: 14 | C7: =COUNTIF(Apr!A5:A18,"Done") -> 0 | D7: =B7-C7 -> 14 | E7: =IF(B7>0,C7/B7,0) -> 0
A8: May | B8: 11 | C8: =COUNTIF(May!A5:A15,"Done") -> 0 | D8: =B8-C8 -> 11 | E8: =IF(B8>0,C8/B8,0) -> 0
A9: June | B9: 11 | C9: =COUNTIF(Jun!A5:A15,"Done") -> 0 | D9: =B9-C9 -> 11 | E9: =IF(B9>0,C9/B9,0) -> 0
A10: July | B10: 14 | C10: =COUNTIF(Jul!A5:A18,"Done") -> 0 | D10: =B10-C10 -> 14 | E10: =IF(B10>0,C10/B10,0) -> 0
A11: August | B11: 11 | C11: =COUNTIF(Aug!A5:A15,"Done") -> 0 | D11: =B11-C11 -> 11 | E11: =IF(B11>0,C11/B11,0) -> 0
A12: September | B12: 11 | C12: =COUNTIF(Sep!A5:A15,"Done") -> 0 | D12: =B12-C12 -> 11 | E12: =IF(B12>0,C12/B12,0) -> 0
A13: October | B13: 14 | C13: =COUNTIF(Oct!A5:A18,"Done") -> 0 | D13: =B13-C13 -> 14 | E13: =IF(B13>0,C13/B13,0) -> 0
A14: November | B14: 11 | C14: =COUNTIF(Nov!A5:A15,"Done") -> 0 | D14: =B14-C14 -> 11 | E14: =IF(B14>0,C14/B14,0) -> 0
A15: December | B15: 11 | C15: =COUNTIF(Dec!A5:A15,"Done") -> 0 | D15: =B15-C15 -> 11 | E15: =IF(B15>0,C15/B15,0) -> 0
A16: TOTAL | B16: =SUM(B4:B15) -> 144 | C16: =SUM(C4:C15) -> 0 | D16: =SUM(D4:D15) -> 144 | E16: =IF(B16>0,C16/B16,0) -> 0

Sheet Jan
A1: January 2026 — Task Checklist
A2: Progress: | C2: =COUNTIF(A5:A18,"Done") & " / 14 complete" -> 0 / 14 complete | E2: =IF(14>0,COUNTIF(A5:A18,"Done")/14,0) -> 0
A4: Status | B4: Day | C4: Property / Fund | D4: Type | E4: Task Description | F4: Owner | G4: Completed By | H4: Date Completed
B5: 8th | C5: 41 Flatbush Ave | D5: AM Fee | E5: Receive JLL Financial Package from JLL. Invoice them for AM Fee - 2.5% | F5: Anthony
B6: 8th | C6: Pref Fund I - Solow | D6: AM Fee | E6: Transfer Solow AM fees to FMC - $5,208 (BofA scheduled) | F6: BofA - automatic
B7: 10th | C7: Paramus Plaza | D7: Reporting | E7: Upload Monthly Management Reports to DRA | F7: Anthony
B8: 20th | C8: 61 S Paramus | D8: AM Fee | E8: Transfer distros from property to FM Paramus Member (BofA scheduled) | F8: BofA - automatic
B9: 20th | C9: Pref Fund II - JPY | D9: Investor Payment | E9: Purchase JPY to Goldman Sachs. Loan from FMC if cash shortfall. | F9: Anthony
B10: 20th | C10: Pref Fund II - JPY | D10: Investor Payment | E10: Send JPY to investors via Goldman Sachs | F10: Anthony
B11: 21st | C11: 61 S Paramus | D11: AM Fee | E11: Transfer AM fee split 48k to FM and 4k to Ring (BofA scheduled) | F11: BofA - automatic
B12: 23rd | C12: 1700 East Putnam | D12: Investor Payment | E12: Send Distros via Appfolio (*Currently Suspended) | F12: Xuan
B13: 23rd | C13: 61 S Paramus | D13: Investor Payment | E13: Send Distros via Appfolio | F13: Anthony
B14: 23rd | C14: One River Centre | D14: Investor Payment | E14: Send Distros via Appfolio (*Xuan sends for now, will be transferred soon to Anthony) | F14: Xuan
B15: 23rd | C15: Paramus Plaza | D15: Investor Payment | E15: Send Distros via Appfolio | F15: Anthony
B16: 23rd | C16: Pref Fund I - Solow | D16: Investor Payment | E16: Send Distros via Appfolio | F16: Anthony
... B18: 25th | C18: Paramus Plaza | D18: AM Fee | E18: Pay Paramus Plaza AM Fee, if cash distro received by DRA | F18: Anthony

Sheet Feb
A1: February 2026 — Task Checklist
A2: Progress: | C2: =COUNTIF(A5:A15,"Done") & " / 11 complete" -> 0 / 11 complete | E2: =IF(11>0,COUNTIF(A5:A15,"Done")/11,0) -> 0
A4: Status | B4: Day | C4: Property / Fund | D4: Type | E4: Task Description | F4: Owner | G4: Completed By | H4: Date Completed
B5: 8th | C5: 41 Flatbush Ave | D5: AM Fee | E5: Receive JLL Financial Package from JLL. Invoice them for AM Fee - 2.5% | F5: Anthony
B6: 8th | C6: Pref Fund I - Solow | D6: AM Fee | E6: Transfer Solow AM fees to FMC - $5,208 (BofA scheduled) | F6: BofA - automatic
B7: 10th | C7: Paramus Plaza | D7: Reporting | E7: Upload Monthly Management Reports to DRA | F7: Anthony
B8: 20th | C8: 61 S Paramus | D8: AM Fee | E8: Transfer distros from property to FM Paramus Member (BofA scheduled) | F8: BofA - automatic
B9: 21st | C9: 61 S Paramus | D9: AM Fee | E9: Transfer AM fee split 48k to FM and 4k to Ring (BofA scheduled) | F9: BofA - automatic
B10: 23rd | C10: 1700 East Putnam | D10: Investor Payment | E10: Send Distros via Appfolio (*Currently Suspended) | F10: Xuan
B11: 23rd | C11: 61 S Paramus | D11: Investor Payment | E11: Send Distros via Appfolio | F11: Anthony
B12: 23rd | C12: One River Centre | D12: Investor Payment | E12: Send Distros via Appfolio (*Xuan sends for now, will be transferred soon to Anthony) | F12: Xuan
B13: 23rd | C13: Paramus Plaza | D13: Investor Payment | E13: Send Distros via Appfolio | F13: Anthony
B14: 23rd | C14: Pref Fund I - Solow | D14: Investor Payment | E14: Send Distros via Appfolio | F14: Anthony
B15: 25th | C15: Paramus Plaza | D15: AM Fee | E15: Pay Paramus Plaza AM Fee, if cash distro received by DRA | F15: Anthony

Sheet Mar
A1: March 2026 — Task Checklist
A2: Progress: | C2: =COUNTIF(A5:A15,"Done") & " / 11 complete" -> 0 / 11 complete | E2: =IF(11>0,COUNTIF(A5:A15,"Done")/11,0) -> 0
A4: Status | B4: Day | C4: Property / Fund | D4: Type | E4: Task Description | F4: Owner | G4: Completed By | H4: Date Completed
B5: 8th | C5: 41 Flatbush Ave | D5: AM Fee | E5: Receive JLL Financial Package from JLL. Invoice them for AM Fee - 2.5% | F5: Anthony
B6: 8th | C6: Pref Fund I - Solow | D6: AM Fee | E6: Transfer Solow AM fees to FMC - $5,208 (BofA scheduled) | F6: BofA - automatic
B7: 10th | C7: Paramus Plaza | D7: Reporting | E7: Upload Monthly Management Reports to DRA | F7: Anthony
B8: 20th | C8: 61 S Paramus | D8: AM Fee | E8: Transfer distros from property to FM Paramus Member (BofA scheduled) | F8: BofA - automatic
B9: 21st | C9: 61 S Paramus | D9: AM Fee | E9: Transfer AM fee split 48k to FM and 4k to Ring (BofA scheduled) | F9: BofA - automatic
B10: 23rd | C10: 1700 East Putnam | D10: Investor Payment | E10: Send Distros via Appfolio (*Currently Suspended) | F10: Xuan
B11: 23rd | C11: 61 S Paramus | D11: Investor Payment | E11: Send Distros via Appfolio | F11: Anthony
B12: 23rd | C12: One River Centre | D12: Investor Payment | E12: Send Distros via Appfolio (*Xuan sends for now, will be transferred soon to Anthony) | F12: Xuan
B13: 23rd | C13: Paramus Plaza | D13: Investor Payment | E13: Send Distros via Appfolio | F13: Anthony
B14: 23rd | C14: Pref Fund I - Solow | D14: Investor Payment | E14: Send Distros via Appfolio | F14: Anthony
B15: 25th | C15: Paramus Plaza | D15: AM Fee | E15: Pay Paramus Plaza AM Fee, if cash distro received by DRA | F15: Anthony

Sheet Apr
A1: April 2026 — Task Checklist
A2: Progress: | C2: =COUNTIF(A5:A18,"Done") & " / 14 complete" -> 0 / 14 complete | E2: =IF(14>0,COUNTIF(A5:A18,"Done")/14,0) -> 0
A4: Status | B4: Day | C4: Property / Fund | D4: Type | E4: Task Description | F4: Owner | G4: Completed By | H4: Date Completed
B5: 8th | C5: 41 Flatbush Ave | D5: AM Fee | E5: Receive JLL Financial Package from JLL. Invoice them for AM Fee - 2.5% | F5: Anthony
B6: 8th | C6: Pref Fund I - Solow | D6: AM Fee | E6: Transfer Solow AM fees to FMC - $5,208 (BofA scheduled) | F6: BofA - automatic
B7: 10th | C7: Paramus Plaza | D7: Reporting | E7: Upload Monthly Management Reports to DRA | F7: Anthony
B8: 20th | C8: 61 S Paramus | D8: AM Fee | E8: Transfer distros from property to FM Paramus Member (BofA scheduled) | F8: BofA - automatic
B9: 20th | C9: Pref Fund II - JPY | D9: Investor Payment | E9: Purchase JPY to Goldman Sachs. Loan from FMC if cash shortfall. | F9: Anthony
B10: 20th | C10: Pref Fund II - JPY | D10: Investor Payment | E10: Send JPY to investors via Goldman Sachs | F10: Anthony
B11: 21st | C11: 61 S Paramus | D11: AM Fee | E11: Transfer AM fee split 48k to FM and 4k to Ring (BofA scheduled) | F11: BofA - automatic
B12: 23rd | C12: 1700 East Putnam | D12: Investor Payment | E12: Send Distros via Appfolio (*Currently Suspended) | F12: Xuan
B13: 23rd | C13: 61 S Paramus | D13: Investor Payment | E13: Send Distros via Appfolio | F13: Anthony
B14: 23rd | C14: One River Centre | D14: Investor Payment | E14: Send Distros via Appfolio (*Xuan sends for now, will be transferred soon to Anthony) | F14: Xuan
B15: 23rd | C15: Paramus Plaza | D15: Investor Payment | E15: Send Distros via Appfolio | F15: Anthony
B16: 23rd | C16: Pref Fund I - Solow | D16: Investor Payment | E16: Send Distros via Appfolio | F16: Anthony
... B18: 25th | C18: Paramus Plaza | D18: AM Fee | E18: Pay Paramus Plaza AM Fee, if cash distro received by DRA | F18: Anthony

Sheet May
A1: May 2026 — Task Checklist
A2: Progress: | C2: =COUNTIF(A5:A15,"Done") & " / 11 complete" -> 0 / 11 complete | E2: =IF(11>0,COUNTIF(A5:A15,"Done")/11,0) -> 0
A4: Status | B4: Day | C4: Property / Fund | D4: Type | E4: Task Description | F4: Owner | G4: Completed By | H4: Date Completed
B5: 8th | C5: 41 Flatbush Ave | D5: AM Fee | E5: Receive JLL Financial Package from JLL. Invoice them for AM Fee - 2.5% | F5: Anthony
B6: 8th | C6: Pref Fund I - Solow | D6: AM Fee | E6: Transfer Solow AM fees to FMC - $5,208 (BofA scheduled) | F6: BofA - automatic
B7: 10th | C7: Paramus Plaza | D7: Reporting | E7: Upload Monthly Management Reports to DRA | F7: Anthony
B8: 20th | C8: 61 S Paramus | D8: AM Fee | E8: Transfer distros from property to FM Paramus Member (BofA scheduled) | F8: BofA - automatic
B9: 21st | C9: 61 S Paramus | D9: AM Fee | E9: Transfer AM fee split 48k to FM and 4k to Ring (BofA scheduled) | F9: BofA - automatic
B10: 23rd | C10: 1700 East Putnam | D10: Investor Payment | E10: Send Distros via Appfolio (*Currently Suspended) | F10: Xuan
B11: 23rd | C11: 61 S Paramus | D11: Investor Payment | E11: Send Distros via Appfolio | F11: Anthony
B12: 23rd | C12: One River Centre | D12: Investor Payment | E12: Send Distros via Appfolio (*Xuan sends for now, will be transferred soon to Anthony) | F12: Xuan
B13: 23rd | C13: Paramus Plaza | D13: Investor Payment | E13: Send Distros via Appfolio | F13: Anthony
B14: 23rd | C14: Pref Fund I - Solow | D14: Investor Payment | E14: Send Distros via Appfolio | F14: Anthony
B15: 25th | C15: Paramus Plaza | D15: AM Fee | E15: Pay Paramus Plaza AM Fee, if cash distro received by DRA | F15: Anthony

Sheet Jun
A1: June 2026 — Task Checklist
A2: Progress: | C2: =COUNTIF(A5:A15,"Done") & " / 11 complete" -> 0 / 11 complete | E2: =IF(11>0,COUNTIF(A5:A15,"Done")/11,0) -> 0
A4: Status | B4: Day | C4: Property / Fund | D4: Type | E4: Task Description | F4: Owner | G4: Completed By | H4: Date Completed
B5: 8th | C5: 41 Flatbush Ave | D5: AM Fee | E5: Receive JLL Financial Package from JLL. Invoice them for AM Fee - 2.5% | F5: Anthony
B6: 8th | C6: Pref Fund I - Solow | D6: AM Fee | E6: Transfer Solow AM fees to FMC - $5,208 (BofA scheduled) | F6: BofA - automatic
B7: 10th | C7: Paramus Plaza | D7: Reporting | E7: Upload Monthly Management Reports to DRA | F7: Anthony
B8: 20th | C8: 61 S Paramus | D8: AM Fee | E8: Transfer distros from property to FM Paramus Member (BofA scheduled) | F8: BofA - automatic
B9: 21st | C9: 61 S Paramus | D9: AM Fee | E9: Transfer AM fee split 48k to FM and 4k to Ring (BofA scheduled) | F9: BofA - automatic
B10: 23rd | C10: 1700 East Putnam | D10: Investor Payment | E10: Send Distros via Appfolio (*Currently Suspended) | F10: Xuan
B11: 23rd | C11: 61 S Paramus | D11: Investor Payment | E11: Send Distros via Appfolio | F11: Anthony
B12: 23rd | C12: One River Centre | D12: Investor Payment | E12: Send Distros via Appfolio (*Xuan sends for now, will be transferred soon to Anthony) | F12: Xuan
B13: 23rd | C13: Paramus Plaza | D13: Investor Payment | E13: Send Distros via Appfolio | F13: Anthony
B14: 23rd | C14: Pref Fund I - Solow | D14: Investor Payment | E14: Send Distros via Appfolio | F14: Anthony
B15: 25th | C15: Paramus Plaza | D15: AM Fee | E15: Pay Paramus Plaza AM Fee, if cash distro received by DRA | F15: Anthony

Sheet Jul
A1: July 2026 — Task Checklist
A2: Progress: | C2: =COUNTIF(A5:A18,"Done") & " / 14 complete" -> 0 / 14 complete | E2: =IF(14>0,COUNTIF(A5:A18,"Done")/14,0) -> 0
A4: Status | B4: Day | C4: Property / Fund | D4: Type | E4: Task Description | F4: Owner | G4: Completed By | H4: Date Completed
B5: 8th | C5: 41 Flatbush Ave | D5: AM Fee | E5: Receive JLL Financial Package from JLL. Invoice them for AM Fee - 2.5% | F5: Anthony
B6: 8th | C6: Pref Fund I - Solow | D6: AM Fee | E6: Transfer Solow AM fees to FMC - $5,208 (BofA scheduled) | F6: BofA - automatic
B7: 10th | C7: Paramus Plaza | D7: Reporting | E7: Upload Monthly Management Reports to DRA | F7: Anthony
B8: 20th | C8: 61 S Paramus | D8: AM Fee | E8: Transfer distros from property to FM Paramus Member (BofA scheduled) | F8: BofA - automatic
B9: 20th | C9: Pref Fund II - JPY | D9: Investor Payment | E9: Purchase JPY to Goldman Sachs. Loan from FMC if cash shortfall. | F9: Anthony
B10: 20th | C10: Pref Fund II - JPY | D10: Investor Payment | E10: Send JPY to investors via Goldman Sachs | F10: Anthony
B11: 21st | C11: 61 S Paramus | D11: AM Fee | E11: Transfer AM fee split 48k to FM and 4k to Ring (BofA scheduled) | F11: BofA - automatic
B12: 23rd | C12: 1700 East Putnam | D12: Investor Payment | E12: Send Distros via Appfolio (*Currently Suspended) | F12: Xuan
B13: 23rd | C13: 61 S Paramus | D13: Investor Payment | E13: Send Distros via Appfolio | F13: Anthony
B14: 23rd | C14: One River Centre | D14: Investor Payment | E14: Send Distros via Appfolio (*Xuan sends for now, will be transferred soon to Anthony) | F14: Xuan
B15: 23rd | C15: Paramus Plaza | D15: Investor Payment | E15: Send Distros via Appfolio | F15: Anthony
B16: 23rd | C16: Pref Fund I - Solow | D16: Investor Payment | E16: Send Distros via Appfolio | F16: Anthony
... B18: 25th | C18: Paramus Plaza | D18: AM Fee | E18: Pay Paramus Plaza AM Fee, if cash distro received by DRA | F18: Anthony

Sheet Aug
A1: August 2026 — Task Checklist
A2: Progress: | C2: =COUNTIF(A5:A15,"Done") & " / 11 complete" -> 0 / 11 complete | E2: =IF(11>0,COUNTIF(A5:A15,"Done")/11,0) -> 0
A4: Status | B4: Day | C4: Property / Fund | D4: Type | E4: Task Description | F4: Owner | G4: Completed By | H4: Date Completed
B5: 8th | C5: 41 Flatbush Ave | D5: AM Fee | E5: Receive JLL Financial Package from JLL. Invoice them for AM Fee - 2.5% | F5: Anthony
B6: 8th | C6: Pref Fund I - Solow | D6: AM Fee | E6: Transfer Solow AM fees to FMC - $5,208 (BofA scheduled) | F6: BofA - automatic
B7: 10th | C7: Paramus Plaza | D7: Reporting | E7: Upload Monthly Management Reports to DRA | F7: Anthony
B8: 20th | C8: 61 S Paramus | D8: AM Fee | E8: Transfer distros from property to FM Paramus Member (BofA scheduled) | F8: BofA - automatic
B9: 21st | C9: 61 S Paramus | D9: AM Fee | E9: Transfer AM fee split 48k to FM and 4k to Ring (BofA scheduled) | F9: BofA - automatic
B10: 23rd | C10: 1700 East Putnam | D10: Investor Payment | E10: Send Distros via Appfolio (*Currently Suspended) | F10: Xuan
B11: 23rd | C11: 61 S Paramus | D11: Investor Payment | E11: Send Distros via Appfolio | F11: Anthony
B12: 23rd | C12: One River Centre | D12: Investor Payment | E12: Send Distros via Appfolio (*Xuan sends for now, will be transferred soon to Anthony) | F12: Xuan
B13: 23rd | C13: Paramus Plaza | D13: Investor Payment | E13: Send Distros via Appfolio | F13: Anthony
B14: 23rd | C14: Pref Fund I - Solow | D14: Investor Payment | E14: Send Distros via Appfolio | F14: Anthony
B15: 25th | C15: Paramus Plaza | D15: AM Fee | E15: Pay Paramus Plaza AM Fee, if cash distro received by DRA | F15: Anthony

Sheet Sep
A1: September 2026 — Task Checklist
A2: Progress: | C2: =COUNTIF(A5:A15,"Done") & " / 11 complete" -> 0 / 11 complete | E2: =IF(11>0,COUNTIF(A5:A15,"Done")/11,0) -> 0
A4: Status | B4: Day | C4: Property / Fund | D4: Type | E4: Task Description | F4: Owner | G4: Completed By | H4: Date Completed
B5: 8th | C5: 41 Flatbush Ave | D5: AM Fee | E5: Receive JLL Financial Package from JLL. Invoice them for AM Fee - 2.5% | F5: Anthony
B6: 8th | C6: Pref Fund I - Solow | D6: AM Fee | E6: Transfer Solow AM fees to FMC - $5,208 (BofA scheduled) | F6: BofA - automatic
B7: 10th | C7: Paramus Plaza | D7: Reporting | E7: Upload Monthly Management Reports to DRA | F7: Anthony
B8: 20th | C8: 61 S Paramus | D8: AM Fee | E8: Transfer distros from property to FM Paramus Member (BofA scheduled) | F8: BofA - automatic
B9: 21st | C9: 61 S Paramus | D9: AM Fee | E9: Transfer AM fee split 48k to FM and 4k to Ring (BofA scheduled) | F9: BofA - automatic
B10: 23rd | C10: 1700 East Putnam | D10: Investor Payment | E10: Send Distros via Appfolio (*Currently Suspended) | F10: Xuan
B11: 23rd | C11: 61 S Paramus | D11: Investor Payment | E11: Send Distros via Appfolio | F11: Anthony
B12: 23rd | C12: One River Centre | D12: Investor Payment | E12: Send Distros via Appfolio (*Xuan sends for now, will be transferred soon to Anthony) | F12: Xuan
B13: 23rd | C13: Paramus Plaza | D13: Investor Payment | E13: Send Distros via Appfolio | F13: Anthony
B14: 23rd | C14: Pref Fund I - Solow | D14: Investor Payment | E14: Send Distros via Appfolio | F14: Anthony
B15: 25th | C15: Paramus Plaza | D15: AM Fee | E15: Pay Paramus Plaza AM Fee, if cash distro received by DRA | F15: Anthony

Sheet Oct
A1: October 2026 — Task Checklist
A2: Progress: | C2: =COUNTIF(A5:A18,"Done") & " / 14 complete" -> 0 / 14 complete | E2: =IF(14>0,COUNTIF(A5:A18,"Done")/14,0) -> 0
A4: Status | B4: Day | C4: Property / Fund | D4: Type | E4: Task Description | F4: Owner | G4: Completed By | H4: Date Completed
B5: 8th | C5: 41 Flatbush Ave | D5: AM Fee | E5: Receive JLL Financial Package from JLL. Invoice them for AM Fee - 2.5% | F5: Anthony
B6: 8th | C6: Pref Fund I - Solow | D6: AM Fee | E6: Transfer Solow AM fees to FMC - $5,208 (BofA scheduled) | F6: BofA - automatic
B7: 10th | C7: Paramus Plaza | D7: Reporting | E7: Upload Monthly Management Reports to DRA | F7: Anthony
B8: 20th | C8: 61 S Paramus | D8: AM Fee | E8: Transfer distros from property to FM Paramus Member (BofA scheduled) | F8: BofA - automatic
B9: 20th | C9: Pref Fund II - JPY | D9: Investor Payment | E9: Purchase JPY to Goldman Sachs. Loan from FMC if cash shortfall. | F9: Anthony
B10: 20th | C10: Pref Fund II - JPY | D10: Investor Payment | E10: Send JPY to investors via Goldman Sachs | F10: Anthony
B11: 21st | C11: 61 S Paramus | D11: AM Fee | E11: Transfer AM fee split 48k to FM and 4k to Ring (BofA scheduled) | F11: BofA - automatic
B12: 23rd | C12: 1700 East Putnam | D12: Investor Payment | E12: Send Distros via Appfolio (*Currently Suspended) | F12: Xuan
B13: 23rd | C13: 61 S Paramus | D13: Investor Payment | E13: Send Distros via Appfolio | F13: Anthony
B14: 23rd | C14: One River Centre | D14: Investor Payment | E14: Send Distros via Appfolio (*Xuan sends for now, will be transferred soon to Anthony) | F14: Xuan
B15: 23rd | C15: Paramus Plaza | D15: Investor Payment | E15: Send Distros via Appfolio | F15: Anthony
B16: 23rd | C16: Pref Fund I - Solow | D16: Investor Payment | E16: Send Distros via Appfolio | F16: Anthony
... B18: 25th | C18: Paramus Plaza | D18: AM Fee | E18: Pay Paramus Plaza AM Fee, if cash distro received by DRA | F18: Anthony

Sheet Nov
A1: November 2026 — Task Checklist
A2: Progress: | C2: =COUNTIF(A5:A15,"Done") & " / 11 complete" -> 0 / 11 complete | E2: =IF(11>0,COUNTIF(A5:A15,"Done")/11,0) -> 0
A4: Status | B4: Day | C4: Property / Fund | D4: Type | E4: Task Description | F4: Owner | G4: Completed By | H4: Date Completed
B5: 8th | C5: 41 Flatbush Ave | D5: AM Fee | E5: Receive JLL Financial Package from JLL. Invoice them for AM Fee - 2.5% | F5: Anthony
B6: 8th | C6: Pref Fund I - Solow | D6: AM Fee | E6: Transfer Solow AM fees to FMC - $5,208 (BofA scheduled) | F6: BofA - automatic
B7: 10th | C7: Paramus Plaza | D7: Reporting | E7: Upload Monthly Management Reports to DRA | F7: Anthony
B8: 20th | C8: 61 S Paramus | D8: AM Fee | E8: Transfer distros from property to FM Paramus Member (BofA scheduled) | F8: BofA - automatic
B9: 21st | C9: 61 S Paramus | D9: AM Fee | E9: Transfer AM fee split 48k to FM and 4k to Ring (BofA scheduled) | F9: BofA - automatic
B10: 23rd | C10: 1700 East Putnam | D10: Investor Payment | E10: Send Distros via Appfolio (*Currently Suspended) | F10: Xuan
B11: 23rd | C11: 61 S Paramus | D11: Investor Payment | E11: Send Distros via Appfolio | F11: Anthony
B12: 23rd | C12: One River Centre | D12: Investor Payment | E12: Send Distros via Appfolio (*Xuan sends for now, will be transferred soon to Anthony) | F12: Xuan
B13: 23rd | C13: Paramus Plaza | D13: Investor Payment | E13: Send Distros via Appfolio | F13: Anthony
B14: 23rd | C14: Pref Fund I - Solow | D14: Investor Payment | E14: Send Distros via Appfolio | F14: Anthony
B15: 25th | C15: Paramus Plaza | D15: AM Fee | E15: Pay Paramus Plaza AM Fee, if cash distro received by DRA | F15: Anthony

Sheet Dec
A1: December 2026 — Task Checklist
A2: Progress: | C2: =COUNTIF(A5:A15,"Done") & " / 11 complete" -> 0 / 11 complete | E2: =IF(11>0,COUNTIF(A5:A15,"Done")/11,0) -> 0
A4: Status | B4: Day | C4: Property / Fund | D4: Type | E4: Task Description | F4: Owner | G4: Completed By | H4: Date Completed
B5: 8th | C5: 41 Flatbush Ave | D5: AM Fee | E5: Receive JLL Financial Package from JLL. Invoice them for AM Fee - 2.5% | F5: Anthony
B6: 8th | C6: Pref Fund I - Solow | D6: AM Fee | E6: Transfer Solow AM fees to FMC - $5,208 (BofA scheduled) | F6: BofA - automatic
B7: 10th | C7: Paramus Plaza | D7: Reporting | E7: Upload Monthly Management Reports to DRA | F7: Anthony
B8: 20th | C8: 61 S Paramus | D8: AM Fee | E8: Transfer distros from property to FM Paramus Member (BofA scheduled) | F8: BofA - automatic
B9: 21st | C9: 61 S Paramus | D9: AM Fee | E9: Transfer AM fee split 48k to FM and 4k to Ring (BofA scheduled) | F9: BofA - automatic
B10: 23rd | C10: 1700 East Putnam | D10: Investor Payment | E10: Send Distros via Appfolio (*Currently Suspended) | F10: Xuan
B11: 23rd | C11: 61 S Paramus | D11: Investor Payment | E11: Send Distros via Appfolio | F11: Anthony
B12: 23rd | C12: One River Centre | D12: Investor Payment | E12: Send Distros via Appfolio (*Xuan sends for now, will be transferred soon to Anthony) | F12: Xuan
B13: 23rd | C13: Paramus Plaza | D13: Investor Payment | E13: Send Distros via Appfolio | F13: Anthony
B14: 23rd | C14: Pref Fund I - Solow | D14: Investor Payment | E14: Send Distros via Appfolio | F14: Anthony
B15: 25th | C15: Paramus Plaza | D15: AM Fee | E15: Pay Paramus Plaza AM Fee, if cash distro received by DRA | F15: Anthony
